langevals_langevals/basic.py
langevals_langevals/competitor_blocklist.py
langevals_langevals/competitor_llm.py
langevals_langevals/competitor_llm_function_call.py
langevals_langevals/exact_match.py
langevals_langevals/llm_answer_match.py
langevals_langevals/llm_boolean.py
langevals_langevals/llm_category.py
langevals_langevals/llm_score.py
langevals_langevals/models/product_sentiment_polarity_openai_experiment_gpt-3.5-turbo_cunning-private-pronghorn_train_82.67_dev_84.0_manually_adjusted.json
langevals_langevals/off_topic.py
langevals_langevals/query_resolution.py
langevals_langevals/similarity.py
langevals_langevals/valid_format.py
langevals_langevals-0.1.13.dist-info/METADATA
langevals_langevals-0.1.13.dist-info/WHEEL
langevals_langevals-0.1.13.dist-info/RECORD
