Metadata-Version: 2.4
Name: langevals-langevals
Version: 0.1.13
Summary: LangEvals core evaluators.
License: MIT
Author: Rogerio Chaves
Author-email: rogerio@langwatch.ai
Requires-Python: >=3.11,<3.13
Classifier: License :: OSI Approved :: MIT License
Classifier: Programming Language :: Python :: 3
Classifier: Programming Language :: Python :: 3.11
Classifier: Programming Language :: Python :: 3.12
Requires-Dist: dspy (>=2.6.8,<3.0.0)
Requires-Dist: jsonschema (>=4.23.0,<5.0.0)
Requires-Dist: langevals-core (>=0.1.18,<0.2.0)
Requires-Dist: litellm (==1.76.0)
Requires-Dist: markdown (>=3.7,<4.0)
Requires-Dist: numpy (>=1.26.4,<2.0.0)
Requires-Dist: openai (>=1.59.7)
Requires-Dist: sqlglot[rs] (>=25.32.0,<26.0.0)
